keepass_http-0.4.4.dist-info/RECORD
keepass_http-0.4.4.dist-info/WHEEL
keepass_http-0.4.4.dist-info/top_level.txt
keepass_http-0.4.4.dist-info/metadata.json
keepass_http-0.4.4.dist-info/METADATA
keepass_http-0.4.4.dist-info/DESCRIPTION.rst
keepass_http-0.4.4.dist-info/entry_points.txt
keepass_http/crypto.py
keepass_http/core.py
keepass_http/__init__.py
keepass_http/utils.py
keepass_http/httpd/requests.py
keepass_http/httpd/server.py
keepass_http/httpd/__init__.py
keepass_http/ui/gui.py
keepass_http/ui/cli.py
keepass_http/ui/__init__.py
keepass_http/scripts/python_keepass_httpd.py
keepass_http/scripts/__init__.py
keepass_http/backends/python_keepass_backend.py
keepass_http/backends/libkeepass_backend.py
keepass_http/backends/__init__.py
keepass_http/conf/require_passphrase.ui
keepass_http/conf/client_connect.ui
keepass_http/conf/should_connect_dialog.ui
keepass_http/conf/logging.conf
