Metadata-Version: 2.0
Name: keepass-http
Version: 0.4.4
Summary: Python Keepass HTTPD for ChromeIPass and PassIFox
Home-page: https://github.com/bh/python-keepass-httpd/
Author: Benjamin Hedrich
Author-email: kiwisauce@pagenotfound.de
License: UNKNOWN
Platform: UNKNOWN
Requires-Dist: colorlog (==2.2.0)
Requires-Dist: daemonize (==2.3)
Requires-Dist: docopt (==0.6.1)
Requires-Dist: enum34 (==1.0)
Requires-Dist: flask (==0.10.1)
Requires-Dist: keepass (==1.2)
Requires-Dist: libkeepass (==0.1.2)
Requires-Dist: lxml (==3.2.1)
Provides-Extra: GUI
Requires-Dist: PySide (==1.2.2); extra == 'GUI'
